msapy/__init__.py
msapy/checks.py
msapy/datastructures.py
msapy/msa.py
msapy/utils.py
msapy-1.7.3.dist-info/METADATA
msapy-1.7.3.dist-info/WHEEL
msapy-1.7.3.dist-info/licenses/LICENSE
msapy-1.7.3.dist-info/RECORD
