Metadata-Version: 2.4
Name: msapy
Version: 1.7.3
Summary: Multi-perturbation Shapley value Analysis (MSA)
Project-URL: Homepage, https://github.com/kuffmode/msa
Project-URL: Repository, https://github.com/kuffmode/msa
Project-URL: Documentation, https://kuffmode.github.io/msa/
Author-email: Kayson Fakhar <kayson.fakhar@gmail.com>, Shrey Dixit <shrey.akshaj@gmail.com>
License: OSI Approved :: MIT License
License-File: LICENSE
Requires-Python: >=3.11
Requires-Dist: fastprogress>=1.0.3
Requires-Dist: joblib>=1.5.1
Requires-Dist: numpy>=2.3.1
Requires-Dist: ordered-set>=4.1.0
Requires-Dist: pandas>=2.3.1
Requires-Dist: pytest>=8.4.1
Requires-Dist: toml>=0.10.2
Requires-Dist: tqdm-joblib>=0.0.4
Requires-Dist: tqdm>=4.67.1
Requires-Dist: typeguard<2.14.0,>=2.13.0
